{
  "schema_version": "1.0",
  "epoch": "10.0",
  "generated_at": "2025-10-21T20:53:24.271322+03:00",
  "git": {
    "commit": "83edb26838e5a1a9970c891d0e2bfa60b25a9bbe",
    "branch": "epoch-v10",
    "tag": null
  },
  "validation": {
    "tri_score": 0.81,
    "tri_threshold": 0.8,
    "resilience_class": "B",
    "maturity_level": 4.0
  },
  "modules": [
    {
      "name": "FEP",
      "description": "Federated Ethical Protocol",
      "tests": 12
    },
    {
      "name": "PCR",
      "description": "Provenance & Consensus Registry",
      "tests": 13
    },
    {
      "name": "AG",
      "description": "Autonomy Governor",
      "tests": 15
    },
    {
      "name": "CIG",
      "description": "Civilizational Intelligence Graph",
      "tests": 7
    },
    {
      "name": "FLE-II",
      "description": "Federated Learning Engine v2",
      "tests": 7
    }
  ],
  "tests": {
    "total": 1074,
    "passing": 1074,
    "failing": 0,
    "runtime_seconds": 2.0
  },
  "archive": {
    "filename": "nova_epoch_v10_archive.tgz",
    "sha256": "6f947c13adb3b15815d3cb45eebd783bef21aa4d610750dadc05d5367b8f68cc"
  },
  "attestation": {
    "file": "attest/phase10_complete.yaml",
    "commit": "83edb26838e5a1a9970c891d0e2bfa60b25a9bbe"
  },
  "lineage": {
    "phase_06": "v6.0-belief-propagation",
    "phase_07": "v7.0-epoch-complete",
    "phase_08": "v8.0-gold",
    "phase_09": "v9.0-complete",
    "phase_10": "v10.0-complete"
  }
}